{
  "query": "automotive tire compressor",
  "pages_fetched": 20,
  "counts_per_page": [
    20,
    20,
    20,
    20,
    20,
    20,
    20,
    20,
    20,
    20,
    20,
    20,
    20,
    20,
    20,
    20,
    20,
    20,
    20,
    20
  ],
  "new_per_page": [
    20,
    2,
    3,
    1,
    3,
    17,
    2,
    4,
    0,
    0,
    8,
    2,
    3,
    1,
    0,
    0,
    0,
    1,
    0,
    0
  ],
  "dup_per_page": [
    0,
    18,
    17,
    19,
    17,
    3,
    18,
    16,
    20,
    20,
    12,
    18,
    17,
    19,
    20,
    20,
    20,
    19,
    20,
    20
  ],
  "deduplication_stats": {
    "total_collected": 400,
    "unique_suppliers": 67,
    "duplicates_removed": 333,
    "duplication_rate": "83.2%"
  },
  "stop_reason": "max_pages_reached",
  "out_dir": "C:\\Users\\dahyunss\\final_sourcing\\alibaba_sourcing3\\1_output\\260226\\sourcing_data\\supplier_search_260226_en\\automotive tire compressor",
  "success": true
}